[
  {
    "timestamp": "2026-01-25T13:13:24.134106+00:00",
    "composite_score": 66.36,
    "category_scores": {
      "CVE": 54.75,
      "KEV": 76.5,
      "EPSS": 62.05
    }
  },
  {
    "timestamp": "2026-01-25T14:03:36.129599+00:00",
    "composite_score": 66.36,
    "category_scores": {
      "CVE": 54.75,
      "KEV": 76.5,
      "EPSS": 62.05
    }
  },
  {
    "timestamp": "2026-01-25T15:03:58.831099+00:00",
    "composite_score": 66.36,
    "category_scores": {
      "CVE": 54.75,
      "KEV": 76.5,
      "EPSS": 62.05
    }
  },
  {
    "timestamp": "2026-01-25T16:04:12.724853+00:00",
    "composite_score": 66.36,
    "category_scores": {
      "CVE": 54.75,
      "KEV": 76.5,
      "EPSS": 62.05
    }
  },
  {
    "timestamp": "2026-01-25T17:03:24.092252+00:00",
    "composite_score": 66.36,
    "category_scores": {
      "CVE": 54.75,
      "KEV": 76.5,
      "EPSS": 62.05
    }
  },
  {
    "timestamp": "2026-01-25T18:04:39.122637+00:00",
    "composite_score": 66.36,
    "category_scores": {
      "CVE": 54.75,
      "KEV": 76.5,
      "EPSS": 62.05
    }
  },
  {
    "timestamp": "2026-01-25T19:03:28.734414+00:00",
    "composite_score": 66.36,
    "category_scores": {
      "CVE": 54.75,
      "KEV": 76.5,
      "EPSS": 62.05
    }
  },
  {
    "timestamp": "2026-01-25T20:04:13.519275+00:00",
    "composite_score": 66.36,
    "category_scores": {
      "CVE": 54.75,
      "KEV": 76.5,
      "EPSS": 62.05
    }
  },
  {
    "timestamp": "2026-01-25T21:03:40.740449+00:00",
    "composite_score": 66.36,
    "category_scores": {
      "CVE": 54.75,
      "KEV": 76.5,
      "EPSS": 62.05
    }
  },
  {
    "timestamp": "2026-01-25T22:03:45.460364+00:00",
    "composite_score": 66.36,
    "category_scores": {
      "CVE": 54.75,
      "KEV": 76.5,
      "EPSS": 62.05
    }
  },
  {
    "timestamp": "2026-01-25T23:04:07.780507+00:00",
    "composite_score": 66.36,
    "category_scores": {
      "CVE": 54.75,
      "KEV": 76.5,
      "EPSS": 62.05
    }
  },
  {
    "timestamp": "2026-01-26T00:15:18.968215+00:00",
    "composite_score": 66.36,
    "category_scores": {
      "CVE": 54.75,
      "KEV": 76.5,
      "EPSS": 62.05
    }
  },
  {
    "timestamp": "2026-01-26T01:32:53.188865+00:00",
    "composite_score": 66.36,
    "category_scores": {
      "CVE": 54.75,
      "KEV": 76.5,
      "EPSS": 62.05
    }
  },
  {
    "timestamp": "2026-01-26T02:49:00.346220+00:00",
    "composite_score": 66.36,
    "category_scores": {
      "CVE": 54.75,
      "KEV": 76.5,
      "EPSS": 62.05
    }
  },
  {
    "timestamp": "2026-01-26T03:38:15.500125+00:00",
    "composite_score": 66.36,
    "category_scores": {
      "CVE": 54.75,
      "KEV": 76.5,
      "EPSS": 62.05
    }
  },
  {
    "timestamp": "2026-01-26T04:26:11.311890+00:00",
    "composite_score": 66.36,
    "category_scores": {
      "CVE": 54.75,
      "KEV": 76.5,
      "EPSS": 62.05
    }
  },
  {
    "timestamp": "2026-01-26T05:12:29.456622+00:00",
    "composite_score": 66.36,
    "category_scores": {
      "CVE": 54.75,
      "KEV": 76.5,
      "EPSS": 62.05
    }
  },
  {
    "timestamp": "2026-01-26T06:06:59.324924+00:00",
    "composite_score": 66.36,
    "category_scores": {
      "CVE": 54.75,
      "KEV": 76.5,
      "EPSS": 62.05
    }
  },
  {
    "timestamp": "2026-01-26T07:09:04.281277+00:00",
    "composite_score": 66.36,
    "category_scores": {
      "CVE": 54.75,
      "KEV": 76.5,
      "EPSS": 62.05
    }
  },
  {
    "timestamp": "2026-01-26T08:05:35.291743+00:00",
    "composite_score": 66.36,
    "category_scores": {
      "CVE": 54.75,
      "KEV": 76.5,
      "EPSS": 62.05
    }
  },
  {
    "timestamp": "2026-01-26T09:09:24.469095+00:00",
    "composite_score": 66.36,
    "category_scores": {
      "CVE": 54.75,
      "KEV": 76.5,
      "EPSS": 62.05
    }
  },
  {
    "timestamp": "2026-01-26T10:05:38.009474+00:00",
    "composite_score": 66.36,
    "category_scores": {
      "CVE": 54.75,
      "KEV": 76.5,
      "EPSS": 62.05
    }
  },
  {
    "timestamp": "2026-01-26T11:04:55.552289+00:00",
    "composite_score": 66.36,
    "category_scores": {
      "CVE": 54.75,
      "KEV": 76.5,
      "EPSS": 62.05
    }
  },
  {
    "timestamp": "2026-01-26T12:06:50.557862+00:00",
    "composite_score": 66.36,
    "category_scores": {
      "CVE": 54.75,
      "KEV": 76.5,
      "EPSS": 62.05
    }
  }
]