[
  {
    "timestamp": "2026-01-24T12:05:36.234416+00:00",
    "composite_score": 66.36,
    "category_scores": {
      "CVE": 54.75,
      "KEV": 76.5,
      "EPSS": 62.05
    }
  },
  {
    "timestamp": "2026-01-24T13:12:21.263396+00:00",
    "composite_score": 66.36,
    "category_scores": {
      "CVE": 54.75,
      "KEV": 76.5,
      "EPSS": 62.05
    }
  },
  {
    "timestamp": "2026-01-24T14:03:51.268039+00:00",
    "composite_score": 66.36,
    "category_scores": {
      "CVE": 54.75,
      "KEV": 76.5,
      "EPSS": 62.05
    }
  },
  {
    "timestamp": "2026-01-24T15:03:46.957985+00:00",
    "composite_score": 66.36,
    "category_scores": {
      "CVE": 54.75,
      "KEV": 76.5,
      "EPSS": 62.05
    }
  },
  {
    "timestamp": "2026-01-24T16:03:56.557530+00:00",
    "composite_score": 66.36,
    "category_scores": {
      "CVE": 54.75,
      "KEV": 76.5,
      "EPSS": 62.05
    }
  },
  {
    "timestamp": "2026-01-24T17:03:00.953893+00:00",
    "composite_score": 66.36,
    "category_scores": {
      "CVE": 54.75,
      "KEV": 76.5,
      "EPSS": 62.05
    }
  },
  {
    "timestamp": "2026-01-24T18:04:31.293995+00:00",
    "composite_score": 66.36,
    "category_scores": {
      "CVE": 54.75,
      "KEV": 76.5,
      "EPSS": 62.05
    }
  },
  {
    "timestamp": "2026-01-24T19:03:21.275509+00:00",
    "composite_score": 66.36,
    "category_scores": {
      "CVE": 54.75,
      "KEV": 76.5,
      "EPSS": 62.05
    }
  },
  {
    "timestamp": "2026-01-24T20:03:45.688158+00:00",
    "composite_score": 66.36,
    "category_scores": {
      "CVE": 54.75,
      "KEV": 76.5,
      "EPSS": 62.05
    }
  },
  {
    "timestamp": "2026-01-24T21:03:32.909806+00:00",
    "composite_score": 66.36,
    "category_scores": {
      "CVE": 54.75,
      "KEV": 76.5,
      "EPSS": 62.05
    }
  },
  {
    "timestamp": "2026-01-24T22:03:50.272473+00:00",
    "composite_score": 66.36,
    "category_scores": {
      "CVE": 54.75,
      "KEV": 76.5,
      "EPSS": 62.05
    }
  },
  {
    "timestamp": "2026-01-24T23:03:49.385816+00:00",
    "composite_score": 66.36,
    "category_scores": {
      "CVE": 54.75,
      "KEV": 76.5,
      "EPSS": 62.05
    }
  },
  {
    "timestamp": "2026-01-25T00:15:30.595104+00:00",
    "composite_score": 66.36,
    "category_scores": {
      "CVE": 54.75,
      "KEV": 76.5,
      "EPSS": 62.05
    }
  },
  {
    "timestamp": "2026-01-25T01:32:37.172622+00:00",
    "composite_score": 66.36,
    "category_scores": {
      "CVE": 54.75,
      "KEV": 76.5,
      "EPSS": 62.05
    }
  },
  {
    "timestamp": "2026-01-25T02:49:00.733415+00:00",
    "composite_score": 66.36,
    "category_scores": {
      "CVE": 54.75,
      "KEV": 76.5,
      "EPSS": 62.05
    }
  },
  {
    "timestamp": "2026-01-25T03:36:09.925509+00:00",
    "composite_score": 66.36,
    "category_scores": {
      "CVE": 54.75,
      "KEV": 76.5,
      "EPSS": 62.05
    }
  },
  {
    "timestamp": "2026-01-25T04:24:54.268588+00:00",
    "composite_score": 66.36,
    "category_scores": {
      "CVE": 54.75,
      "KEV": 76.5,
      "EPSS": 62.05
    }
  },
  {
    "timestamp": "2026-01-25T05:10:13.809727+00:00",
    "composite_score": 66.36,
    "category_scores": {
      "CVE": 54.75,
      "KEV": 76.5,
      "EPSS": 62.05
    }
  },
  {
    "timestamp": "2026-01-25T06:05:19.075156+00:00",
    "composite_score": 66.36,
    "category_scores": {
      "CVE": 54.75,
      "KEV": 76.5,
      "EPSS": 62.05
    }
  },
  {
    "timestamp": "2026-01-25T07:04:49.904696+00:00",
    "composite_score": 66.36,
    "category_scores": {
      "CVE": 54.75,
      "KEV": 76.5,
      "EPSS": 62.05
    }
  },
  {
    "timestamp": "2026-01-25T08:04:21.121609+00:00",
    "composite_score": 66.36,
    "category_scores": {
      "CVE": 54.75,
      "KEV": 76.5,
      "EPSS": 62.05
    }
  },
  {
    "timestamp": "2026-01-25T09:04:09.316357+00:00",
    "composite_score": 66.36,
    "category_scores": {
      "CVE": 54.75,
      "KEV": 76.5,
      "EPSS": 62.05
    }
  },
  {
    "timestamp": "2026-01-25T10:03:48.508674+00:00",
    "composite_score": 66.36,
    "category_scores": {
      "CVE": 54.75,
      "KEV": 76.5,
      "EPSS": 62.05
    }
  },
  {
    "timestamp": "2026-01-25T11:03:39.384839+00:00",
    "composite_score": 66.36,
    "category_scores": {
      "CVE": 54.75,
      "KEV": 76.5,
      "EPSS": 62.05
    }
  }
]